empty_my_fridge/README.md
empty_my_fridge/__init__.py
empty_my_fridge/config.py
empty_my_fridge/db.sqlite3
empty_my_fridge/manage.py
empty_my_fridge/__pycache__/config.cpython-38.pyc
empty_my_fridge/c_files/food_network.py
empty_my_fridge/c_files/librecipe_parsing.so
empty_my_fridge/c_files/recipe_parse.cpp
empty_my_fridge/c_files/recipe_parse.h
empty_my_fridge/c_files/recipe_parsing.dll
empty_my_fridge/c_files/recipe_parsing.o
empty_my_fridge/c_files/recipe_parsing.so
empty_my_fridge/cpanel/__init__.py
empty_my_fridge/cpanel/asgi.py
empty_my_fridge/cpanel/settings.py
empty_my_fridge/cpanel/urls.py
empty_my_fridge/cpanel/wsgi.py
empty_my_fridge/cpanel/__pycache__/__init__.cpython-38.pyc
empty_my_fridge/cpanel/__pycache__/settings.cpython-38.pyc
empty_my_fridge/cpanel/__pycache__/urls.cpython-38.pyc
empty_my_fridge/cpanel/__pycache__/wsgi.cpython-38.pyc
empty_my_fridge/empty_my_fridge/__init__.py
empty_my_fridge/empty_my_fridge/allrecipes.py
empty_my_fridge/empty_my_fridge/urls.py
empty_my_fridge/empty_my_fridge/views.py
empty_my_fridge/empty_my_fridge/__pycache__/__init__.cpython-38.pyc
empty_my_fridge/empty_my_fridge/__pycache__/allrecipes.cpython-38.pyc
empty_my_fridge/empty_my_fridge/__pycache__/urls.cpython-38.pyc
empty_my_fridge/empty_my_fridge/__pycache__/views.cpython-38.pyc
empty_my_fridge/empty_my_fridge/model/category.py
empty_my_fridge/empty_my_fridge/model/message.py
empty_my_fridge/empty_my_fridge/model/recipes.py
empty_my_fridge/empty_my_fridge/model/route.py
empty_my_fridge/empty_my_fridge/model/user.py
empty_my_fridge/empty_my_fridge/model/__pycache__/Fridge.cpython-38.pyc
empty_my_fridge/empty_my_fridge/model/__pycache__/category.cpython-38.pyc
empty_my_fridge/empty_my_fridge/model/__pycache__/message.cpython-38.pyc
empty_my_fridge/empty_my_fridge/model/__pycache__/recipes.cpython-38.pyc
empty_my_fridge/empty_my_fridge/model/__pycache__/route.cpython-38.pyc
empty_my_fridge/empty_my_fridge/model/__pycache__/user.cpython-38.pyc
empty_my_fridge-1.1.6.dist-info/LICENSE
empty_my_fridge-1.1.6.dist-info/METADATA
empty_my_fridge-1.1.6.dist-info/WHEEL
empty_my_fridge-1.1.6.dist-info/entry_points.txt
empty_my_fridge-1.1.6.dist-info/top_level.txt
empty_my_fridge-1.1.6.dist-info/RECORD
