Metadata-Version: 2.1
Name: empty-my-fridge
Version: 1.1.6
Summary: Get your Daily Recipes
Home-page: https://github.com/edwarddubi/empty_my_fridge_django
Author: Charles Charlestin, Rebecca Boes, Cyan Perez, Randolph Maynes, Edward Mensah
License: MI
Platform: UNKNOWN
Classifier: Environment :: Web Environment
Classifier: Programming Language :: Python :: 3
Classifier: License :: OSI Approved :: MIT License
Classifier: Operating System :: OS Independent
Requires-Python: >=3.6
Requires-Dist: Django (>=3.0.7)
Requires-Dist: pyrebase
Requires-Dist: beautifulsoup4
